nest_zc/__init__.py
nest_zc/hello.py
nest_zc/main.py
nest_zc/robot.py
nest_zc/ros2_types.py
nest_zc-0.1.5.dist-info/METADATA
nest_zc-0.1.5.dist-info/WHEEL
nest_zc-0.1.5.dist-info/entry_points.txt
nest_zc-0.1.5.dist-info/licenses/LICENSE
nest_zc-0.1.5.dist-info/RECORD
