Metadata-Version: 2.4
Name: nest-zc
Version: 0.1.5
Summary: Example
Author-email: You <you@example.com>
License: Copyright (c) <year> <copyright holders>
License-File: LICENSE
Requires-Python: >=3.8
Requires-Dist: eclipse-zenoh==1.3.4
Requires-Dist: pycdr2==1.0.0
